maps/__init__.py
maps/visualR.py
mapsrouting-0.1.11.dist-info/METADATA
mapsrouting-0.1.11.dist-info/WHEEL
mapsrouting-0.1.11.dist-info/top_level.txt
mapsrouting-0.1.11.dist-info/RECORD
